{
  "name": "Centre nautique Cité de l'Eau — Publier",
  "commune": "Publier",
  "gps": {
    "lat": 46.39,
    "lng": 6.547
  },
  "type": "aquaparc",
  "hours": "Ouvert toute l'année, horaires étendus en vacances scolaires. Détail des créneaux grand public sur le site.",
  "prices": {
    "from": 7.9,
    "currency": "EUR",
    "tiers": [],
    "is_free": false,
    "note": "Adulte ~5-8 € · enfant ~3-5 € · pass espace bien-être"
  },
  "access_pmr": {
    "status": "accessible",
    "detail": "Baignade accessible à tous avec équipements PMR : cabine adaptée dans chaque vestiaire, fauteuil roulant pour transfert et siège hydraulique pour entrer/sortir de l'eau",
    "equipment": [
      "fauteuil_tout_terrain",
      "sanitaire_adapte"
    ],
    "handiplage_level": null,
    "source_url": "https://centre-nautique.ville-publier.fr",
    "source_name": "Centre nautique Cité de l'Eau (site officiel)"
  },
  "parking": null,
  "transport": null,
  "season": "Toute l'année",
  "winter": null,
  "official_url": "https://centre-nautique.ville-publier.fr",
  "last_verified": "2026-07-19"
}
