{
  "name": "Ciné Léman",
  "commune": "Thonon-les-Bains",
  "gps": {
    "lat": 46.37,
    "lng": 6.4811
  },
  "type": "cinema",
  "hours": "Programmation hebdomadaire renouvelée le mercredi. Séances en soirée toute la semaine, après-midi en cas de jour férié, mercredi, week-end et vacances scolaires.",
  "prices": {
    "from": null,
    "currency": "EUR",
    "tiers": [],
    "is_free": false,
    "note": "Plein tarif ~9-12 € · réduit ~6-8 € · Pass Culture · carnet abonnement"
  },
  "access_pmr": null,
  "parking": null,
  "transport": {
    "source": "transport.data.gouv.fr",
    "license": "Licence Etalab 2.0",
    "verified": "2026-06-15",
    "stops": [
      {
        "name": "Thonon-les-Bains",
        "operator": "SNCF (TER)",
        "distance_m": 121,
        "lines": []
      },
      {
        "name": "Les Arts",
        "operator": "Cars Région Haute-Savoie",
        "distance_m": 192,
        "lines": [
          "Y03",
          "Y91"
        ]
      },
      {
        "name": "Lycée Versoie",
        "operator": "Cars Région Haute-Savoie",
        "distance_m": 1019,
        "lines": [
          "Y03",
          "Y91"
        ]
      }
    ]
  },
  "season": "Toute l'année",
  "official_url": "https://www.cineleman.fr/",
  "last_verified": null
}
