{
  "name": "Patinoire Jean Régis",
  "commune": "Annecy",
  "gps": {
    "lat": 45.8975,
    "lng": 6.1322
  },
  "type": "patinoire",
  "hours": "Horaires du Patinoire Jean Régis : Mer + sam + dim 14h-18h. Vendredi soir 20h-23h disco. Vacances tous les jours. Vérifié sur le site officiel le 24 mai 2026 — sous réserve de modifications saisonnières.",
  "prices": {
    "from": 4.6,
    "currency": "EUR",
    "tiers": [],
    "is_free": false,
    "note": "4,60 € + location patins 3,40 €"
  },
  "access_pmr": {
    "status": "partiel",
    "detail": "Acceslibre (complexe Jean Regis): places de parking adaptees et reservees dans l'etablissement, entree de plain-pied d'au moins 80 cm; fiche incomplete (29%).",
    "equipment": [
      "parking_pmr",
      "place_pmr"
    ],
    "handiplage_level": null,
    "source_url": "https://acceslibre.beta.gouv.fr/app/74-annecy/a/piscine/erp/piscine-jean-regis/",
    "source_name": "Acceslibre"
  },
  "parking": "Gratuit sur site",
  "transport": {
    "source": "transport.data.gouv.fr",
    "license": "Licence Etalab 2.0",
    "verified": "2026-06-15",
    "stops": [
      {
        "name": "DEPOT BATEAUX",
        "operator": "SIBRA",
        "distance_m": 76,
        "lines": []
      },
      {
        "name": "PONTON ANNECY",
        "operator": "SIBRA",
        "distance_m": 84,
        "lines": []
      },
      {
        "name": "PISCINE MARQUISATS",
        "operator": "SIBRA",
        "distance_m": 86,
        "lines": [
          "13",
          "15",
          "26",
          "27"
        ]
      }
    ]
  },
  "season": "Toute l'année",
  "winter": null,
  "official_url": "https://www.annecy.fr/activites/sport/patinoire",
  "last_verified": "2026-06-05"
}
