{
  "slug": "cinema-le-france-thonon",
  "category": "cinema",
  "commune": "Thonon-les-Bains",
  "postal_code": "74200",
  "department": "Haute-Savoie",
  "latitude": 46.3712,
  "longitude": 6.4789,
  "hero_image": "/generique-cinema.jpg",
  "hero_credit": null,
  "official_site_url": null,
  "price_from": null,
  "price_currency": "EUR",
  "price_tiers": [],
  "sources": [],
  "verify_flags": [
    "GPS non vérifié",
    "site web propre à vérifier"
  ],
  "date_published_human": "3 juin 2026",
  "date_modified_human": "3 juin 2026",
  "schema_org": {
    "type": "MovieTheater",
    "is_free": false,
    "public_access": true,
    "amenities": []
  },
  "sparse_data": true,
  "research_log": [
    "Créé 3 juin 2026 — cinéma art et essai. Site propre à confirmer."
  ],
  "partners": [],
  "gallery_photos": [],
  "i18n": {
    "fr": {
      "name": "Le France",
      "name_alternates": [],
      "meta_title": "Le France — Cinéma en Haute-Savoie | Loisirs 74",
      "meta_description": "Cinéma art et essai de 3 salles à Thonon-les-Bains.",
      "hero": {
        "badge": "Cinéma",
        "lead": "Cinéma art et essai de 3 salles à Thonon-les-Bains."
      },
      "hero_alt": "Le France, cinéma en Haute-Savoie",
      "facts": {
        "type": "Cinéma",
        "access": null,
        "tarif": null,
        "commune": null,
        "duration": null,
        "best_season": null
      },
      "body": {
        "what_is": "Le France est un cinéma classé art et essai de 3 salles à Thonon-les-Bains, programmation d'auteur et patrimoine."
      },
      "activities": [],
      "practical_info": [],
      "how_to_get_there": {
        "car": null,
        "public_transport": null,
        "bike": null
      },
      "when_to_visit": null,
      "events": [],
      "faq": [],
      "schema_amenities": []
    },
    "en": {
      "name": "Le France",
      "name_alternates": [],
      "meta_title": "Le France — Cinéma en Haute-Savoie | Loisirs 74",
      "meta_description": "Cinéma art et essai de 3 salles à Thonon-les-Bains.",
      "hero": {
        "badge": "Cinéma",
        "lead": "Cinéma art et essai de 3 salles à Thonon-les-Bains."
      },
      "hero_alt": "Le France, cinéma en Haute-Savoie",
      "facts": {
        "type": "Cinéma",
        "access": null,
        "tarif": null,
        "commune": null,
        "duration": null,
        "best_season": null
      },
      "body": {
        "what_is": "Le France est un cinéma classé art et essai de 3 salles à Thonon-les-Bains, programmation d'auteur et patrimoine."
      },
      "activities": [],
      "practical_info": [],
      "how_to_get_there": {
        "car": null,
        "public_transport": null,
        "bike": null
      },
      "when_to_visit": null,
      "events": [],
      "faq": [],
      "schema_amenities": []
    },
    "de": {
      "name": "Le France",
      "name_alternates": [],
      "meta_title": "Le France — Cinéma en Haute-Savoie | Loisirs 74",
      "meta_description": "Cinéma art et essai de 3 salles à Thonon-les-Bains.",
      "hero": {
        "badge": "Cinéma",
        "lead": "Cinéma art et essai de 3 salles à Thonon-les-Bains."
      },
      "hero_alt": "Le France, cinéma en Haute-Savoie",
      "facts": {
        "type": "Cinéma",
        "access": null,
        "tarif": null,
        "commune": null,
        "duration": null,
        "best_season": null
      },
      "body": {
        "what_is": "Le France est un cinéma classé art et essai de 3 salles à Thonon-les-Bains, programmation d'auteur et patrimoine."
      },
      "activities": [],
      "practical_info": [],
      "how_to_get_there": {
        "car": null,
        "public_transport": null,
        "bike": null
      },
      "when_to_visit": null,
      "events": [],
      "faq": [],
      "schema_amenities": []
    },
    "it": {
      "name": "Le France",
      "name_alternates": [],
      "meta_title": "Le France — Cinéma en Haute-Savoie | Loisirs 74",
      "meta_description": "Cinéma art et essai de 3 salles à Thonon-les-Bains.",
      "hero": {
        "badge": "Cinéma",
        "lead": "Cinéma art et essai de 3 salles à Thonon-les-Bains."
      },
      "hero_alt": "Le France, cinéma en Haute-Savoie",
      "facts": {
        "type": "Cinéma",
        "access": null,
        "tarif": null,
        "commune": null,
        "duration": null,
        "best_season": null
      },
      "body": {
        "what_is": "Le France est un cinéma classé art et essai de 3 salles à Thonon-les-Bains, programmation d'auteur et patrimoine."
      },
      "activities": [],
      "practical_info": [],
      "how_to_get_there": {
        "car": null,
        "public_transport": null,
        "bike": null
      },
      "when_to_visit": null,
      "events": [],
      "faq": [],
      "schema_amenities": []
    },
    "es": {
      "name": "Le France",
      "name_alternates": [],
      "meta_title": "Le France — Cinéma en Haute-Savoie | Loisirs 74",
      "meta_description": "Cinéma art et essai de 3 salles à Thonon-les-Bains.",
      "hero": {
        "badge": "Cinéma",
        "lead": "Cinéma art et essai de 3 salles à Thonon-les-Bains."
      },
      "hero_alt": "Le France, cinéma en Haute-Savoie",
      "facts": {
        "type": "Cinéma",
        "access": null,
        "tarif": null,
        "commune": null,
        "duration": null,
        "best_season": null
      },
      "body": {
        "what_is": "Le France est un cinéma classé art et essai de 3 salles à Thonon-les-Bains, programmation d'auteur et patrimoine."
      },
      "activities": [],
      "practical_info": [],
      "how_to_get_there": {
        "car": null,
        "public_transport": null,
        "bike": null
      },
      "when_to_visit": null,
      "events": [],
      "faq": [],
      "schema_amenities": []
    }
  },
  "featured_businesses": [],
  "google_check": {
    "checked": "2026-06-04",
    "query": "Le France Thonon-les-Bains Haute-Savoie France",
    "match": "Thonon-les-Bains",
    "place_id": "ChIJk_8GcYk-jEcRgJa65CqrCAQ",
    "status": "UNKNOWN",
    "website": "http://www.ville-thonon.fr/",
    "stored_website": null,
    "rating": null,
    "rating_count": null,
    "hours": null,
    "google_lat": 46.3710387,
    "google_lng": 6.481942399999999,
    "gps_drift_m": 234
  }
}