{
  "slug": "parcours-aventure-de-sciez",
  "category": "attraction",
  "commune": "Sciez",
  "postal_code": "74140",
  "department": "Haute-Savoie",
  "latitude": 46.3312,
  "longitude": 6.3705,
  "hero_image": "https://upload.wikimedia.org/wikipedia/commons/b/b8/Accrobranche_floreval_2.jpg",
  "hero_credit": "Forest park · Wikimedia Commons",
  "booking_url": "https://www.parcoursaventure-sciez.com/home/",
  "booking_domain": "parcoursaventure-sciez.com",
  "booking_verified_date": "2026-05-14",
  "official_site_url": "https://www.parcoursaventure-sciez.com/home/",
  "price_from": 13,
  "price_currency": "EUR",
  "price_tiers": [
    {
      "name": "Parcours découverte adulte",
      "price": 14,
      "note": "À partir de 5 ans et 1,10 m minimum"
    },
    {
      "name": "Parcours découverte enfant",
      "price": 13,
      "note": "De 1,10 m à 1,40 m"
    },
    {
      "name": "Grand parcours adulte",
      "price": 20,
      "note": "À partir de 1,40 m"
    },
    {
      "name": "Grand parcours enfant",
      "price": 18,
      "note": "À partir de 1,40 m"
    },
    {
      "name": "Tarif groupe",
      "price": null,
      "note": "Réduction de 2 € par entrée à partir de 8 personnes"
    }
  ],
  "sources": [
    "https://www.parcoursaventure-sciez.com/home/",
    "https://www.thononlesbains.com/activite/grand-parcours-du-parcours-aventure-de-sciez-sciez/",
    "https://en.wikipedia.org/wiki/Sciez",
    "https://hautesavoiemontblanc-tourisme.com/en/offers/accrobranche-adventure-course-sciez-en-5885444/"
  ],
  "verify_flags": [
    "Tarifs vérifiés sur le site officiel le 14 mai 2026",
    "Horaires vérifiés sur le site officiel le 14 mai 2026",
    "GPS approximatif — adresse 409 route du Moulin de la Glacière utilisée pour localisation",
    "Le parc est aussi appelé La Forêt de l'Aventure de Sciez dans certaines sources",
    "Label Famille Plus en partenariat avec l'office de tourisme de Sciez"
  ],
  "date_published_human": "14 mai 2026",
  "date_modified_human": "14 mai 2026",
  "schema_org": {
    "type": "TouristAttraction",
    "is_free": false,
    "public_access": true,
    "amenities": [
      "Parking gratuit",
      "Aire de pique-nique",
      "Plus de 40 ateliers",
      "Parcours de difficultés variables"
    ]
  },
  "sparse_data": false,
  "research_log": [],
  "partners": [
    {
      "tier": "recommended",
      "type": "restaurant",
      "name": "Château de Coudrée — Restaurant François Ier",
      "url": "https://chateau-hotel-coudree.com/",
      "i18n_placeholder": true,
      "i18n": {
        "fr": {
          "description": "Restaurant gastronomique dans un château du XIIe siècle au bord du Léman, avenue de Coudrée à Sciez. 3 toques Gault&Millau. À proximité."
        },
        "en": {
          "description": "Restaurant gastronomique dans un château du XIIe siècle au bord du Léman, avenue de Coudrée à Sciez. 3 toques Gault&Millau. À proximité."
        },
        "de": {
          "description": "Restaurant gastronomique dans un château du XIIe siècle au bord du Léman, avenue de Coudrée à Sciez. 3 toques Gault&Millau. À proximité."
        },
        "it": {
          "description": "Restaurant gastronomique dans un château du XIIe siècle au bord du Léman, avenue de Coudrée à Sciez. 3 toques Gault&Millau. À proximité."
        },
        "es": {
          "description": "Restaurant gastronomique dans un château du XIIe siècle au bord du Léman, avenue de Coudrée à Sciez. 3 toques Gault&Millau. À proximité."
        }
      }
    },
    {
      "tier": "invite",
      "invite_type": "commerce",
      "i18n": {
        "fr": {
          "title": "Un commerce à Sciez ?",
          "desc": "Partagez horaires et spécialités avec les visiteurs du Parcours Aventure de Sciez."
        }
      }
    },
    {
      "tier": "recommended",
      "type": "hebergement",
      "name": "Château de Coudrée****",
      "url": "https://chateau-hotel-coudree.com/",
      "i18n_placeholder": true,
      "i18n": {
        "fr": {
          "description": "Hôtel 4 étoiles indépendant dans un château du XIIe siècle avec plage privée, avenue de Coudrée à Sciez. "
        },
        "en": {
          "description": "Hôtel 4 étoiles indépendant dans un château du XIIe siècle avec plage privée, avenue de Coudrée à Sciez. "
        },
        "de": {
          "description": "Hôtel 4 étoiles indépendant dans un château du XIIe siècle avec plage privée, avenue de Coudrée à Sciez. "
        },
        "it": {
          "description": "Hôtel 4 étoiles indépendant dans un château du XIIe siècle avec plage privée, avenue de Coudrée à Sciez. "
        },
        "es": {
          "description": "Hôtel 4 étoiles indépendant dans un château du XIIe siècle avec plage privée, avenue de Coudrée à Sciez. "
        }
      }
    }
  ],
  "gallery_photos": [],
  "i18n": {
    "fr": {
      "name": "Parcours Aventure de Sciez",
      "name_alternates": [
        "La Forêt de l'Aventure de Sciez",
        "Parcours Aventure Sciez sur Léman",
        "Accrobranche Sciez"
      ],
      "meta_title": "Parcours Aventure Sciez · Tarifs et horaires (74140)",
      "meta_description": "Parc accrobranche dans les chênes centenaires du Domaine de Coudrée. Plus de 40 ateliers, 2 parcours, tarifs dès 13 €. Label Famille Plus.",
      "hero": {
        "badge": "Payant · Sur réservation",
        "lead": "Parc d'accrobranche au cœur d'une forêt de chênes centenaires du Domaine de Coudrée, entre Thonon-les-Bains et Douvaine, avec plus de 40 ateliers dans les arbres."
      },
      "hero_alt": "Parcours aventure dans les chênes centenaires du Domaine de Coudrée à Sciez, Haute-Savoie",
      "facts": {
        "type": "Parc accrobranche",
        "access": "Payant",
        "tarif": "À partir de 13 € (parcours découverte)",
        "commune": "Sciez",
        "parking": "Gratuit sur place",
        "duration": "1 h (parcours découverte) à 3h30 (grand parcours)",
        "best_season": "Avril – novembre",
        "dogs": "Non autorisés",
        "stroller": "Non adapté"
      },
      "body": {
        "what_is": "<p>Le <strong>Parcours Aventure de Sciez</strong> est un parc d'accrobranche situé au cœur du Domaine de Coudrée, entre Thonon-les-Bains et Douvaine, à deux pas du lac Léman. Le parc est installé dans une forêt de chênes centenaires et propose plus de 40 ateliers acrobatiques dans les arbres : tyroliennes, ponts de cordes, passerelles, échelles, balançoires, liane de Tarzan et autres obstacles à franchir en toute sécurité.</p><p>Deux parcours sont proposés : un <strong>parcours découverte</strong> pour les enfants à partir de 5 ans et mesurant au minimum 1,10 m, d'une durée d'environ 1 heure, et un <strong>grand parcours</strong> pour les adultes et enfants à partir de 1,40 m, offrant environ 3h30 d'aventure. Les moins de 18 ans doivent obligatoirement être accompagnés d'un adulte sur les parcours. Le parc est labellisé Famille Plus en partenariat avec l'office de tourisme de Sciez et respecte les normes AFNOR de construction et d'exploitation (établissement n° ET001435).</p>"
      },
      "activities": [
        {
          "title": "Grand parcours (à partir de 1,40 m)",
          "tag": null,
          "description": "Évoluez d'arbre en arbre pendant 3h30 sur plus de 40 ateliers : tyroliennes, ponts de singe, poutres, échelles, balançoires et liane de Tarzan. Pour adultes et enfants à partir de 1,40 m."
        },
        {
          "title": "Parcours découverte (à partir de 1,10 m)",
          "tag": null,
          "description": "Parcours adapté aux enfants dès 5 ans et mesurant au minimum 1,10 m. Environ 1 heure d'activité pour découvrir les sensations de l'accrobranche en toute sécurité."
        },
        {
          "title": "Tyroliennes et ateliers sensations",
          "tag": null,
          "description": "Testez les différentes tyroliennes du parc, la liane de Tarzan, la balançoire géante et la balancelle pour des sensations garanties au-dessus de la forêt."
        },
        {
          "title": "Aire de pique-nique",
          "tag": null,
          "description": "Profitez de l'aire de pique-nique sur place pour vous restaurer et vous reposer entre deux parcours. Tables disponibles gratuitement."
        }
      ],
      "practical_info": [
        {
          "k": "Adresse",
          "v": "409 route du Moulin de la Glacière, 74140 Sciez"
        },
        {
          "k": "Horaires",
          "v": "Avril et novembre : mercredis, week-ends et jours fériés de 11h à 19h. Vacances de Pâques et Toussaint : tous les jours de 11h à 19h. Juillet et août : tous les jours de 11h à 19h. Dernier briefing à 17h. Possibilité d'ouverture plus tôt le matin pour les groupes sur réservation. Vérifié sur le site officiel le 14 mai 2026 — sous réserve de modifications saisonnières.",
          "verified": "2026-05-14"
        },
        {
          "k": "Tarifs",
          "v": "Parcours découverte : adulte 14 €, enfant 13 €. Grand parcours : adulte 20 €, enfant 18 €. Tarif groupe (à partir de 8 personnes) : -2 € par entrée. Vérifié le 14 mai 2026.",
          "verified": "2026-05-14"
        },
        {
          "k": "Réservation",
          "v": "Conseillée, en ligne sur parcoursaventure-sciez.com ou par téléphone au 04 50 72 51 86. Achat également possible sur place selon disponibilités."
        },
        {
          "k": "Parking",
          "v": "Gratuit sur place"
        },
        {
          "k": "Animaux",
          "v": "Non autorisés"
        },
        {
          "k": "Accessibilité",
          "v": "Non adapté aux personnes à mobilité réduite. Taille minimum requise : 1,10 m pour le parcours découverte, 1,40 m pour le grand parcours."
        },
        {
          "k": "Contact",
          "v": "Tél. : +33 4 50 72 51 86 · Mobile : +33 6 70 63 34 73 · Email : info@parcoursaventure-sciez.com",
          "verified": "2026-05-14"
        },
        {
          "k": "Équipement",
          "v": "Matériel de sécurité fourni (baudrier, mousquetons, ligne de vie continue). Prévoir des chaussures fermées."
        }
      ],
      "how_to_get_there": {
        "car": "Depuis Thonon-les-Bains (9 km), prendre la D1005 direction Douvaine puis suivre la signalisation vers Sciez. Le parc se trouve au 409 route du Moulin de la Glacière, derrière le musée de Préhistoire et Les Aigles du Léman dans le Domaine de Coudrée. Parking gratuit sur place.",
        "public_transport": "Ligne de bus Thonon-Douvaine-Genève, arrêt à Sciez. Vérifier les horaires et correspondances auprès de Thonon Agglomération. Le parc est ensuite accessible à pied (environ 15 minutes depuis le centre de Sciez).",
        "bike": "Accessible via la véloroute du Léman (itinéraire longeant le lac entre Thonon et Genève). Stationnement vélos disponible sur place."
      },
      "when_to_visit": "La meilleure période pour visiter le Parcours Aventure de Sciez s'étend d'avril à novembre, avec une ouverture totale en juillet et août (tous les jours de 11h à 19h). Le parc est également ouvert les week-ends et mercredis en avril et novembre, ainsi que tous les jours durant les vacances de Pâques et de la Toussaint. En cas de mauvais temps (pluie forte, vent violent), le parc peut fermer temporairement pour des raisons de sécurité — il est conseillé de contacter l'établissement avant de vous déplacer. Les matinées d'été sont plus calmes et offrent des conditions idéales pour profiter de la fraîcheur de la forêt.",
      "events": null,
      "faq": [
        {
          "q": "Comment réserver le Parcours Aventure de Sciez ?",
          "a": "Réservation en ligne sur le site officiel parcoursaventure-sciez.com ou par téléphone au 04 50 72 51 86 (mobile : 06 70 63 34 73). Achat possible également sur place aux caisses du Parcours Aventure de Sciez selon les disponibilités. La réservation est conseillée, surtout en haute saison."
        },
        {
          "q": "Quel est le tarif du Parcours Aventure de Sciez ?",
          "a": "Le tarif du parcours découverte au Parcours Aventure de Sciez est de 14 € pour un adulte et 13 € pour un enfant. Le grand parcours coûte 20 € pour un adulte et 18 € pour un enfant. Tarif groupe (à partir de 8 personnes) : -2 € par entrée. Vérifié le 14 mai 2026."
        },
        {
          "q": "Quelles sont les horaires du Parcours Aventure de Sciez ?",
          "a": "Le Parcours Aventure de Sciez est ouvert d'avril à novembre : mercredis, week-ends et jours fériés de 11h à 19h. Juillet et août : tous les jours de 11h à 19h. Vacances de Pâques et Toussaint : tous les jours de 11h à 19h. Dernier briefing à 17h. Vérifié sur le site officiel le 14 mai 2026 — sous réserve de modifications saisonnières."
        },
        {
          "q": "Quelle est la taille minimum requise pour le Parcours Aventure de Sciez ?",
          "a": "Le parcours découverte du Parcours Aventure de Sciez est accessible dès 5 ans avec une taille minimum de 1,10 m. Le grand parcours nécessite une taille minimum de 1,40 m. Les moins de 18 ans doivent obligatoirement être accompagnés d'un adulte sur les parcours."
        },
        {
          "q": "Y a-t-il un parking au Parcours Aventure de Sciez ?",
          "a": "Oui. Le Parcours Aventure de Sciez dispose d'un parking gratuit sur place au 409 route du Moulin de la Glacière à Sciez, dans le Domaine de Coudrée."
        },
        {
          "q": "Peut-on pique-niquer sur place au Parcours Aventure de Sciez ?",
          "a": "Oui. Le Parcours Aventure de Sciez met à disposition une aire de pique-nique avec des tables gratuites pour se restaurer et se reposer entre deux parcours."
        }
      ],
      "schema_amenities": [
        "Parking gratuit",
        "Aire de pique-nique",
        "Plus de 40 ateliers",
        "Matériel de sécurité fourni",
        "Label Famille Plus"
      ]
    },
    "en": {
      "name": "Parcours Aventure de Sciez",
      "name_alternates": [
        "La Forêt de l'Aventure de Sciez",
        "Parcours Aventure Sciez sur Léman",
        "Accrobranche Sciez"
      ],
      "meta_title": "Parcours Aventure Sciez · Rates and hours (74140)",
      "meta_description": "Treetop adventure park among century-old oak trees in the Coudrée Estate. Over 40 activities, 2 courses, from €13. Family Plus certified.",
      "hero": {
        "badge": "Paid · Reservation required",
        "lead": "Treetop adventure park in the heart of a forest of century-old oak trees in the Coudrée Estate, between Thonon-les-Bains and Douvaine, with over 40 activities in the trees."
      },
      "hero_alt": "Adventure course among century-old oak trees in the Coudrée Estate at Sciez, Haute-Savoie",
      "facts": {
        "type": "Treetop adventure park",
        "access": "Paid",
        "tarif": "From €13 (discovery course)",
        "commune": "Sciez",
        "parking": "Free on-site",
        "duration": "1 hour (discovery course) to 3.5 hours (main course)",
        "best_season": "April – November",
        "dogs": "Not allowed",
        "stroller": "Not suitable"
      },
      "body": {
        "what_is": "<p>The <strong>Parcours Aventure de Sciez</strong> is a treetop adventure park located in the heart of the Coudrée Estate, between Thonon-les-Bains and Douvaine, just a short distance from Lake Léman. The park is set in a forest of century-old oak trees and offers over 40 acrobatic activities in the trees: zip-lines, rope bridges, walkways, ladders, swings, Tarzan swings and other obstacles to be crossed safely.</p><p>Two courses are offered: a <strong>discovery course</strong> for children aged 5 and over and measuring at least 1.10 m, lasting approximately 1 hour, and a <strong>main course</strong> for adults and children from 1.40 m, offering approximately 3.5 hours of adventure. Children under 18 must be accompanied by an adult on the courses. The park is certified Family Plus in partnership with the Sciez tourist office and complies with AFNOR standards for construction and operation (establishment no. ET001435).</p>"
      },
      "activities": [
        {
          "title": "Main course (from 1.40 m)",
          "tag": null,
          "description": "Move from tree to tree for 3.5 hours over more than 40 activities: zip-lines, monkey bridges, beams, ladders, swings and Tarzan swing. For adults and children from 1.40 m."
        },
        {
          "title": "Discovery course (from 1.10 m)",
          "tag": null,
          "description": "Course adapted for children aged 5 and over and measuring at least 1.10 m. Approximately 1 hour of activity to discover the sensations of tree climbing safely."
        },
        {
          "title": "Zip-lines and thrill activities",
          "tag": null,
          "description": "Try the various zip-lines in the park, the Tarzan swing, the giant swing and the pendulum swing for guaranteed thrills above the forest."
        },
        {
          "title": "Picnic area",
          "tag": null,
          "description": "Make use of the picnic area on-site to refresh and rest between courses. Tables available free of charge."
        }
      ],
      "practical_info": [
        {
          "k": "Address",
          "v": "409 route du Moulin de la Glacière, 74140 Sciez"
        },
        {
          "k": "Hours",
          "v": "April and November: Wednesdays, weekends and public holidays 11am–7pm. Easter and All Saints holidays: Daily 11am–7pm. July and August: Daily 11am–7pm. Last briefing at 5pm. Early morning opening available for groups by reservation. Verified on the official website on 14 May 2026 — subject to seasonal changes."
        },
        {
          "k": "Rates",
          "v": "Discovery course: adult €14, child €13. Main course: adult €20, child €18. Group rate (from 8 people): -€2 per entry. Verified on 14 May 2026."
        },
        {
          "k": "Reservation",
          "v": "Recommended, online at parcoursaventure-sciez.com or by phone on 04 50 72 51 86. Purchase also possible on-site according to availability."
        },
        {
          "k": "Parking",
          "v": "Free on-site"
        },
        {
          "k": "Animals",
          "v": "Not allowed"
        },
        {
          "k": "Accessibility",
          "v": "Not suitable for people with reduced mobility. Minimum height required: 1.10 m for discovery course, 1.40 m for main course."
        },
        {
          "k": "Contact",
          "v": "Tel: +33 4 50 72 51 86 · Mobile: +33 6 70 63 34 73 · Email: info@parcoursaventure-sciez.com"
        },
        {
          "k": "Equipment",
          "v": "Safety equipment provided (harness, carabiners, continuous safety line). Wear closed-toe shoes."
        }
      ],
      "how_to_get_there": {
        "car": "From Thonon-les-Bains (9 km), take the D1005 toward Douvaine then follow signs to Sciez. The park is located at 409 route du Moulin de la Glacière, behind the Prehistory Museum and Les Aigles du Léman in the Coudrée Estate. Free parking on-site.",
        "public_transport": "Bus line Thonon–Douvaine–Geneva, stop at Sciez. Check timetables and connections with Thonon Agglomération. The park is then accessible on foot (approximately 15 minutes from Sciez town centre).",
        "bike": "Accessible via the Lake Léman cycle route (route along the lake between Thonon and Geneva). Bike parking available on-site."
      },
      "when_to_visit": "The best time to visit Parcours Aventure de Sciez runs from April to November, with full opening in July and August (daily 11am–7pm). The park is also open on weekends and Wednesdays in April and November, as well as daily during Easter and All Saints holidays. In bad weather (heavy rain, strong wind), the park may close temporarily for safety reasons — it is advisable to contact the establishment before you travel. Summer mornings are quieter and offer ideal conditions to enjoy the coolness of the forest.",
      "events": null,
      "faq": [
        {
          "q": "How do I book Parcours Aventure de Sciez?",
          "a": "Book online at the official website parcoursaventure-sciez.com or by phone on 04 50 72 51 86 (mobile: 06 70 63 34 73). Purchase is also possible on-site at the Parcours Aventure de Sciez ticket office according to availability. Reservation is recommended, especially during peak season."
        },
        {
          "q": "What is the admission price for Parcours Aventure de Sciez?",
          "a": "The admission price for the discovery course at Parcours Aventure de Sciez is €14 for an adult and €13 for a child. The main course costs €20 for an adult and €18 for a child. Group rate (from 8 people): -€2 per entry. Verified on 14 May 2026."
        },
        {
          "q": "What are the hours for Parcours Aventure de Sciez?",
          "a": "Parcours Aventure de Sciez is open April to November: Wednesdays, weekends and public holidays 11am–7pm. July and August: Daily 11am–7pm. Easter and All Saints holidays: Daily 11am–7pm. Last briefing at 5pm. Verified on the official website on 14 May 2026 — subject to seasonal changes."
        },
        {
          "q": "What is the minimum height required for Parcours Aventure de Sciez?",
          "a": "The discovery course at Parcours Aventure de Sciez is accessible from age 5 with a minimum height of 1.10 m. The main course requires a minimum height of 1.40 m. Children under 18 must be accompanied by an adult on the courses."
        },
        {
          "q": "Is there parking at Parcours Aventure de Sciez?",
          "a": "Yes. Parcours Aventure de Sciez has free parking on-site at 409 route du Moulin de la Glacière in Sciez, in the Coudrée Estate."
        },
        {
          "q": "Can I have a picnic at Parcours Aventure de Sciez?",
          "a": "Yes. Parcours Aventure de Sciez provides a picnic area with free tables where you can eat and rest between courses."
        }
      ],
      "schema_amenities": [
        "Free parking",
        "Picnic area",
        "Over 40 activities",
        "Safety equipment provided",
        "Family Plus certified"
      ]
    },
    "de": {
      "name": "Parcours Aventure de Sciez",
      "name_alternates": [
        "La Forêt de l'Aventure de Sciez",
        "Parcours Aventure Sciez sur Léman",
        "Accrobranche Sciez"
      ],
      "meta_title": "Parcours Aventure Sciez · Tarife und Öffnungszeiten (74140)",
      "meta_description": "Kletterpark in hundertjährigen Eichen des Domaine de Coudrée. Über 40 Stationen, 2 Parcours, Tarife ab 13 €. Familienfreundlich zertifiziert.",
      "hero": {
        "badge": "Gebührenpflichtig · Nach Reservierung",
        "lead": "Kletterpark inmitten eines Waldes mit hundertjährigen Eichen des Domaine de Coudrée, zwischen Thonon-les-Bains und Douvaine, mit über 40 Stationen in den Bäumen."
      },
      "hero_alt": "Abenteuerparcours in den hundertjährigen Eichen des Domaine de Coudrée in Sciez, Haute-Savoie",
      "facts": {
        "type": "Kletterpark",
        "access": "Gebührenpflichtig",
        "tarif": "Ab 13 € (Entdeckungsparcours)",
        "commune": "Sciez",
        "parking": "Kostenlos vor Ort",
        "duration": "1 h (Entdeckungsparcours) bis 3h30 (Großer Parcours)",
        "best_season": "April – November",
        "dogs": "Nicht erlaubt",
        "stroller": "Nicht geeignet"
      },
      "body": {
        "what_is": "<p>Der <strong>Parcours Aventure de Sciez</strong> ist ein Kletterpark im Herzen des Domaine de Coudrée, zwischen Thonon-les-Bains und Douvaine, unweit des Genfersees. Der Park befindet sich in einem Wald mit hundertjährigen Eichen und bietet über 40 akrobatische Stationen in den Bäumen: Seilrutschen, Seilbrücken, Stege, Leitern, Schaukeln, Tarzan-Lianen und weitere Hindernisse zum sicheren Überwinden.</p><p>Zwei Parcours stehen zur Verfügung: ein <strong>Entdeckungsparcours</strong> für Kinder ab 5 Jahren mit einer Mindestgröße von 1,10 m, mit einer Dauer von etwa 1 Stunde, und ein <strong>Großer Parcours</strong> für Erwachsene und Kinder ab 1,40 m, der etwa 3h30 Abenteuer bietet. Kinder unter 18 Jahren müssen zwingend von einem Erwachsenen begleitet werden. Der Park ist familienfreundlich zertifiziert in Partnerschaft mit dem Tourismusbüro Sciez und entspricht den AFNOR-Normen für Bau und Betrieb (Einrichtung Nr. ET001435).</p>"
      },
      "activities": [
        {
          "title": "Großer Parcours (ab 1,40 m)",
          "tag": null,
          "description": "Bewältigen Sie über 3h30 mehr als 40 Stationen von Baum zu Baum: Seilrutschen, Affenbrücken, Balken, Leitern, Schaukeln und Tarzan-Liane. Für Erwachsene und Kinder ab 1,40 m."
        },
        {
          "title": "Entdeckungsparcours (ab 1,10 m)",
          "tag": null,
          "description": "Parcours speziell für Kinder ab 5 Jahren mit einer Mindestgröße von 1,10 m. Etwa 1 Stunde Aktivität, um die Sensationen des Kletterparks sicher zu entdecken."
        },
        {
          "title": "Seilrutschen und Spannungsstationen",
          "tag": null,
          "description": "Testen Sie die verschiedenen Seilrutschen des Parks, die Tarzan-Liane, die Riesenschaukel und die Schaukelstange für garantierte Sensationen über dem Wald."
        },
        {
          "title": "Picknickbereich",
          "tag": null,
          "description": "Nutzen Sie den Picknickbereich vor Ort, um sich zu verpflegen und zwischen den Parcours auszuruhen. Tische kostenlos verfügbar."
        }
      ],
      "practical_info": [
        {
          "k": "Adresse",
          "v": "409 route du Moulin de la Glacière, 74140 Sciez"
        },
        {
          "k": "Öffnungszeiten",
          "v": "April und November: Mittwoch, Wochenenden und Feiertage von 11h bis 19h. Oster- und Herbstferien: täglich von 11h bis 19h. Juli und August: täglich von 11h bis 19h. Letzte Einweisung um 17h. Möglichkeit der früheren Morgenöffnung für Gruppen nach Reservierung. Überprüft auf der offiziellen Website am 14. Mai 2026 — unter Vorbehalt saisonaler Änderungen.",
          "verified": "2026-05-14"
        },
        {
          "k": "Tarife",
          "v": "Entdeckungsparcours: Erwachsener 14 €, Kind 13 €. Großer Parcours: Erwachsener 20 €, Kind 18 €. Gruppentarif (ab 8 Personen): -2 € pro Eintritt. Überprüft am 14. Mai 2026.",
          "verified": "2026-05-14"
        },
        {
          "k": "Reservierung",
          "v": "Empfohlen, online auf parcoursaventure-sciez.com oder telefonisch unter +33 4 50 72 51 86. Kauf auch vor Ort je nach Verfügbarkeit möglich."
        },
        {
          "k": "Parkplatz",
          "v": "Kostenlos vor Ort"
        },
        {
          "k": "Haustiere",
          "v": "Nicht erlaubt"
        },
        {
          "k": "Barrierefreiheit",
          "v": "Nicht geeignet für Personen mit eingeschränkter Mobilität. Mindestgröße erforderlich: 1,10 m für den Entdeckungsparcours, 1,40 m für den Großen Parcours."
        },
        {
          "k": "Kontakt",
          "v": "Tel.: +33 4 50 72 51 86 · Mobil: +33 6 70 63 34 73 · E-Mail: info@parcoursaventure-sciez.com",
          "verified": "2026-05-14"
        },
        {
          "k": "Ausrüstung",
          "v": "Sicherheitsausrüstung vorhanden (Gurt, Karabiner, durchgehende Sicherungsleine). Geschlossene Schuhe erforderlich."
        }
      ],
      "how_to_get_there": {
        "car": "Von Thonon-les-Bains (9 km) die D1005 Richtung Douvaine nehmen und dann der Beschilderung nach Sciez folgen. Der Park befindet sich unter der Adresse 409 route du Moulin de la Glacière, hinter dem Prähistorie-Museum und den Adlern des Genfersees im Domaine de Coudrée. Kostenloser Parkplatz vor Ort.",
        "public_transport": "Buslinie Thonon-Douvaine-Genf, Haltestelle Sciez. Fahrpläne und Anschlüsse bei Thonon Agglomération überprüfen. Der Park ist danach zu Fuß erreichbar (etwa 15 Minuten vom Zentrum Sciez).",
        "bike": "Zugänglich über die Véloroute du Léman (Route am Seeufer zwischen Thonon und Genf). Fahrradparkplätze vorhanden."
      },
      "when_to_visit": "Die beste Jahreszeit zum Besuch des Parcours Aventure de Sciez erstreckt sich von April bis November, mit vollständiger Öffnung im Juli und August (täglich von 11h bis 19h). Der Park ist auch an Wochenenden und Mittwoch im April und November geöffnet sowie täglich während der Oster- und Herbstferien. Bei schlechtem Wetter (starker Regen, starker Wind) kann der Park vorübergehend aus Sicherheitsgründen geschlossen werden – es wird empfohlen, die Einrichtung vor Ihrem Besuch zu kontaktieren. Die Sommermorgende sind ruhiger und bieten ideale Bedingungen, um die Kühle des Waldes zu genießen.",
      "events": null,
      "faq": [
        {
          "q": "Wie reserviert man den Parcours Aventure de Sciez?",
          "a": "Reservierung online auf der offiziellen Website parcoursaventure-sciez.com oder telefonisch unter +33 4 50 72 51 86 (Mobil: 06 70 63 34 73). Kauf auch an der Kasse des Parcours Aventure de Sciez je nach Verfügbarkeit möglich. Die Reservierung wird empfohlen, besonders in der Hochsaison."
        },
        {
          "q": "Was kostet der Eintritt für den Parcours Aventure de Sciez?",
          "a": "Der Entdeckungsparcours des Parcours Aventure de Sciez kostet 14 € für Erwachsene und 13 € für Kinder. Der Große Parcours kostet 20 € für Erwachsene und 18 € für Kinder. Gruppentarif (ab 8 Personen): -2 € pro Eintritt. Überprüft am 14. Mai 2026."
        },
        {
          "q": "Welche Öffnungszeiten hat der Parcours Aventure de Sciez?",
          "a": "Der Parcours Aventure de Sciez ist von April bis November geöffnet: Mittwoch, Wochenenden und Feiertage von 11h bis 19h. Juli und August: täglich von 11h bis 19h. Oster- und Herbstferien: täglich von 11h bis 19h. Letzte Einweisung um 17h. Überprüft auf der offiziellen Website am 14. Mai 2026 – unter Vorbehalt saisonaler Änderungen."
        },
        {
          "q": "Welche Mindestgröße ist für den Parcours Aventure de Sciez erforderlich?",
          "a": "Der Entdeckungsparcours des Parcours Aventure de Sciez ist für Kinder ab 5 Jahren mit einer Mindestgröße von 1,10 m zugänglich. Der Große Parcours erfordert eine Mindestgröße von 1,40 m. Kinder unter 18 Jahren müssen zwingend von einem Erwachsenen begleitet werden."
        },
        {
          "q": "Gibt es einen Parkplatz beim Parcours Aventure de Sciez?",
          "a": "Ja. Der Parcours Aventure de Sciez verfügt über einen kostenlosen Parkplatz vor Ort unter der Adresse 409 route du Moulin de la Glacière in Sciez, im Domaine de Coudrée."
        },
        {
          "q": "Kann man beim Parcours Aventure de Sciez picknick?",
          "a": "Ja. Der Parcours Aventure de Sciez stellt einen Picknickbereich mit kostenlosen Tischen zur Verfügung, um sich zu verpflegen und zwischen den Parcours auszuruhen."
        }
      ],
      "schema_amenities": [
        "Kostenloser Parkplatz",
        "Picknickbereich",
        "Über 40 Stationen",
        "Sicherheitsausrüstung vorhanden",
        "Familienfreundlich zertifiziert"
      ]
    },
    "it": {
      "name": "Parcours Aventure de Sciez",
      "name_alternates": [
        "La Forêt de l'Aventure de Sciez",
        "Parcours Aventure Sciez sur Léman",
        "Accrobranche Sciez"
      ],
      "meta_title": "Parcours Aventure Sciez · Tariffe e orari (74140)",
      "meta_description": "Parco avventura negli antichi querceti del Domaine de Coudrée. Più di 40 percorsi, 2 circuiti, tariffe da 13 €. Etichetta Famiglia Plus.",
      "hero": {
        "badge": "A pagamento · Su prenotazione",
        "lead": "Parco avventura nel cuore di una foresta di querce centenarie del Domaine de Coudrée, tra Thonon-les-Bains e Douvaine, con più di 40 percorsi acrobatici negli alberi."
      },
      "hero_alt": "Percorso avventura nelle querce centenarie del Domaine de Coudrée a Sciez, Alta Savoia",
      "facts": {
        "type": "Parco avventura",
        "access": "A pagamento",
        "tarif": "A partire da 13 € (percorso scoperta)",
        "commune": "Sciez",
        "parking": "Gratuito in loco",
        "duration": "1 h (percorso scoperta) a 3h30 (grand circuito)",
        "best_season": "Aprile – novembre",
        "dogs": "Non consentiti",
        "stroller": "Non adatto"
      },
      "body": {
        "what_is": "<p>Il <strong>Parcours Aventure de Sciez</strong> è un parco avventura situato nel cuore del Domaine de Coudrée, tra Thonon-les-Bains e Douvaine, a pochi passi dal lago di Ginevra. Il parco è allestito in una foresta di querce centenarie e propone più di 40 percorsi acrobatici negli alberi: zip-line, ponti di corda, passerelle, scale, altalene, liana di Tarzan e altri ostacoli da superare in tutta sicurezza.</p><p>Sono proposti due percorsi: un <strong>percorso scoperta</strong> per i bambini a partire da 5 anni e di altezza minima 1,10 m, della durata di circa 1 ora, e un <strong>grand circuito</strong> per adulti e bambini a partire da 1,40 m, che offre circa 3h30 di avventura. I minori di 18 anni devono essere obbligatoriamente accompagnati da un adulto sui percorsi. Il parco è etichettato Famiglia Plus in collaborazione con l'ufficio del turismo di Sciez e rispetta gli standard AFNOR di costruzione e gestione (struttura n° ET001435).</p>"
      },
      "activities": [
        {
          "title": "Grand circuito (a partire da 1,40 m)",
          "tag": null,
          "description": "Evolvetevi di albero in albero per 3h30 su più di 40 percorsi: zip-line, ponti di scimmia, travi, scale, altalene e liana di Tarzan. Per adulti e bambini a partire da 1,40 m."
        },
        {
          "title": "Percorso scoperta (a partire da 1,10 m)",
          "tag": null,
          "description": "Percorso adatto ai bambini da 5 anni e di altezza minima 1,10 m. Circa 1 ora di attività per scoprire le sensazioni del parco avventura in tutta sicurezza."
        },
        {
          "title": "Zip-line e percorsi adrenalinici",
          "tag": null,
          "description": "Provate le diverse zip-line del parco, la liana di Tarzan, l'altalena gigante e la balancella per sensazioni garantite sopra la foresta."
        },
        {
          "title": "Area picnic",
          "tag": null,
          "description": "Approfittate dell'area picnic in loco per rinfrescarvi e riposarvi tra un percorso e l'altro. Tavoli disponibili gratuitamente."
        }
      ],
      "practical_info": [
        {
          "k": "Indirizzo",
          "v": "409 route du Moulin de la Glacière, 74140 Sciez"
        },
        {
          "k": "Orari",
          "v": "Aprile e novembre: mercoledì, fine settimana e giorni festivi dalle 11:00 alle 19:00. Vacanze di Pasqua e Ognissanti: tutti i giorni dalle 11:00 alle 19:00. Luglio e agosto: tutti i giorni dalle 11:00 alle 19:00. Ultimo briefing alle 17:00. Possibilità di apertura più presto al mattino per gruppi su prenotazione. Verificato sul sito ufficiale il 14 maggio 2026 — salvo modifiche stagionali.",
          "verified": "2026-05-14"
        },
        {
          "k": "Tariffe",
          "v": "Percorso scoperta: adulto 14 €, bambino 13 €. Grand circuito: adulto 20 €, bambino 18 €. Tariffa gruppo (a partire da 8 persone): -2 € per ingresso. Verificato il 14 maggio 2026."
        },
        {
          "k": "Prenotazione",
          "v": "Consigliata, online su parcoursaventure-sciez.com o per telefono al 04 50 72 51 86. Acquisto possibile anche in loco in base alla disponibilità."
        },
        {
          "k": "Parcheggio",
          "v": "Gratuito in loco"
        },
        {
          "k": "Animali",
          "v": "Non consentiti"
        },
        {
          "k": "Accessibilità",
          "v": "Non adatto alle persone con mobilità ridotta. Altezza minima richiesta: 1,10 m per il percorso scoperta, 1,40 m per il grand circuito."
        },
        {
          "k": "Contatti",
          "v": "Tel.: +33 4 50 72 51 86 · Mobile: +33 6 70 63 34 73 · Email: info@parcoursaventure-sciez.com",
          "verified": "2026-05-14"
        },
        {
          "k": "Attrezzatura",
          "v": "Equipaggiamento di sicurezza fornito (cintura di sicurezza, moschettoni, linea di vita continua). Prevedere scarpe chiuse."
        }
      ],
      "how_to_get_there": {
        "car": "Da Thonon-les-Bains (9 km), prendere la D1005 direzione Douvaine poi seguire la segnaletica verso Sciez. Il parco si trova al 409 route du Moulin de la Glacière, dietro il museo di Preistoria e Les Aigles du Léman nel Domaine de Coudrée. Parcheggio gratuito in loco.",
        "public_transport": "Linea autobus Thonon-Douvaine-Ginevra, fermata a Sciez. Verificare orari e corrispondenze presso Thonon Agglomération. Il parco è quindi accessibile a piedi (circa 15 minuti dal centro di Sciez).",
        "bike": "Accessibile tramite la pista ciclabile del Lemano (itinerario che costeggia il lago tra Thonon e Ginevra). Parcheggio biciclette disponibile in loco."
      },
      "when_to_visit": "Il periodo migliore per visitare il Parcours Aventure de Sciez va da aprile a novembre, con apertura totale a luglio e agosto (tutti i giorni dalle 11:00 alle 19:00). Il parco è inoltre aperto nei fine settimana e mercoledì ad aprile e novembre, così come tutti i giorni durante le vacanze di Pasqua e Ognissanti. In caso di maltempo (pioggia forte, vento violento), il parco può chiudere temporaneamente per motivi di sicurezza — si consiglia di contattare la struttura prima di recarvi. Le mattinate estive sono più tranquille e offrono condizioni ideali per godere della freschezza della foresta.",
      "events": null,
      "faq": [
        {
          "q": "Come prenotare il Parcours Aventure de Sciez?",
          "a": "Prenotazione online sul sito ufficiale parcoursaventure-sciez.com o per telefono al 04 50 72 51 86 (mobile: 06 70 63 34 73). Acquisto possibile anche in loco alle casse del Parcours Aventure de Sciez in base alla disponibilità. La prenotazione è consigliata, soprattutto in alta stagione."
        },
        {
          "q": "Qual è la tariffa del Parcours Aventure de Sciez?",
          "a": "La tariffa del percorso scoperta al Parcours Aventure de Sciez è di 14 € per un adulto e 13 € per un bambino. Il grand circuito costa 20 € per un adulto e 18 € per un bambino. Tariffa gruppo (a partire da 8 persone): -2 € per ingresso. Verificato il 14 maggio 2026."
        },
        {
          "q": "Quali sono gli orari del Parcours Aventure de Sciez?",
          "a": "Il Parcours Aventure de Sciez è aperto da aprile a novembre: mercoledì, fine settimana e giorni festivi dalle 11:00 alle 19:00. Luglio e agosto: tutti i giorni dalle 11:00 alle 19:00. Vacanze di Pasqua e Ognissanti: tutti i giorni dalle 11:00 alle 19:00. Ultimo briefing alle 17:00. Verificato sul sito ufficiale il 14 maggio 2026 — salvo modifiche stagionali."
        },
        {
          "q": "Quale è l'altezza minima richiesta per il Parcours Aventure de Sciez?",
          "a": "Il percorso scoperta del Parcours Aventure de Sciez è accessibile da 5 anni con altezza minima di 1,10 m. Il grand circuito richiede un'altezza minima di 1,40 m. I minori di 18 anni devono essere obbligatoriamente accompagnati da un adulto sui percorsi."
        },
        {
          "q": "C'è un parcheggio al Parcours Aventure de Sciez?",
          "a": "Sì. Il Parcours Aventure de Sciez dispone di un parcheggio gratuito in loco al 409 route du Moulin de la Glacière a Sciez, nel Domaine de Coudrée."
        },
        {
          "q": "Si può fare un picnic al Parcours Aventure de Sciez?",
          "a": "Sì. Il Parcours Aventure de Sciez mette a disposizione un'area picnic con tavoli gratuiti per rinfrescarvi e riposarvi tra un percorso e l'altro."
        }
      ],
      "schema_amenities": [
        "Parcheggio gratuito",
        "Area picnic",
        "Più di 40 percorsi",
        "Equipaggiamento di sicurezza fornito",
        "Etichetta Famiglia Plus"
      ]
    },
    "es": {
      "name": "Parcours Aventure de Sciez",
      "name_alternates": [
        "La Forêt de l'Aventure de Sciez",
        "Parcours Aventure Sciez sur Léman",
        "Accrobranche Sciez"
      ],
      "meta_title": "Parcours Aventure Sciez · Tarifas y horarios (74140)",
      "meta_description": "Parque de aventura entre robles centenarios del Domaine de Coudrée. Más de 40 talleres, 2 recorridos, desde 13 €. Etiqueta Familia Plus.",
      "hero": {
        "badge": "De pago · Con reserva",
        "lead": "Parque de aventura en el corazón de un bosque de robles centenarios del Domaine de Coudrée, entre Thonon-les-Bains y Douvaine, con más de 40 talleres en los árboles."
      },
      "hero_alt": "Recorrido de aventura en los robles centenarios del Domaine de Coudrée en Sciez, Alta Saboya",
      "facts": {
        "type": "Parque de aventura",
        "access": "De pago",
        "tarif": "A partir de 13 € (recorrido descubrimiento)",
        "commune": "Sciez",
        "parking": "Gratuito en el lugar",
        "duration": "1 h (recorrido descubrimiento) a 3h30 (gran recorrido)",
        "best_season": "Abril – noviembre",
        "dogs": "No permitidos",
        "stroller": "No adaptado"
      },
      "body": {
        "what_is": "<p>El <strong>Parcours Aventure de Sciez</strong> es un parque de aventura situado en el corazón del Domaine de Coudrée, entre Thonon-les-Bains y Douvaine, muy cerca del lago Léman. El parque está instalado en un bosque de robles centenarios y propone más de 40 talleres acrobáticos en los árboles: tirolinas, puentes de cuerda, pasarelas, escaleras, columpios, liana de Tarzán y otros obstáculos para franquear en completa seguridad.</p><p>Se proponen dos recorridos: un <strong>recorrido descubrimiento</strong> para niños a partir de 5 años y midiendo como mínimo 1,10 m, con una duración de aproximadamente 1 hora, y un <strong>gran recorrido</strong> para adultos y niños a partir de 1,40 m, ofreciendo aproximadamente 3h30 de aventura. Los menores de 18 años deben estar obligatoriamente acompañados por un adulto en los recorridos. El parque tiene la etiqueta Familia Plus en asociación con la oficina de turismo de Sciez y respeta las normas AFNOR de construcción y explotación (establecimiento nº ET001435).</p>"
      },
      "activities": [
        {
          "title": "Gran recorrido (a partir de 1,40 m)",
          "tag": null,
          "description": "Evolucione de árbol en árbol durante 3h30 en más de 40 talleres: tirolinas, puentes de monos, vigas, escaleras, columpios y liana de Tarzán. Para adultos y niños a partir de 1,40 m."
        },
        {
          "title": "Recorrido descubrimiento (a partir de 1,10 m)",
          "tag": null,
          "description": "Recorrido adaptado para niños desde 5 años y midiendo como mínimo 1,10 m. Aproximadamente 1 hora de actividad para descubrir las sensaciones de la aventura en los árboles en completa seguridad."
        },
        {
          "title": "Tirolinas y talleres de sensaciones",
          "tag": null,
          "description": "Pruebe las diferentes tirolinas del parque, la liana de Tarzán, el columpio gigante y la balancela para sensaciones garantizadas sobre el bosque."
        },
        {
          "title": "Área de picnic",
          "tag": null,
          "description": "Disfrute del área de picnic en el lugar para comer y descansar entre dos recorridos. Mesas disponibles gratuitamente."
        }
      ],
      "practical_info": [
        {
          "k": "Dirección",
          "v": "409 route du Moulin de la Glacière, 74140 Sciez"
        },
        {
          "k": "Horarios",
          "v": "Abril y noviembre: miércoles, fines de semana y días festivos de 11h a 19h. Vacaciones de Pascua y Todos los Santos: todos los días de 11h a 19h. Julio y agosto: todos los días de 11h a 19h. Último briefing a las 17h. Posibilidad de apertura más temprano por la mañana para grupos con reserva. Verificado en el sitio oficial el 14 de mayo de 2026 — bajo reserva de modificaciones estacionales.",
          "verified": "2026-05-14"
        },
        {
          "k": "Tarifas",
          "v": "Recorrido descubrimiento: adulto 14 €, niño 13 €. Gran recorrido: adulto 20 €, niño 18 €. Tarifa grupo (a partir de 8 personas): -2 € por entrada. Verificado el 14 de mayo de 2026.",
          "verified": "2026-05-14"
        },
        {
          "k": "Reserva",
          "v": "Recomendada, en línea en parcoursaventure-sciez.com o por teléfono al 04 50 72 51 86. Compra también posible en el lugar según disponibilidades."
        },
        {
          "k": "Aparcamiento",
          "v": "Gratuito en el lugar"
        },
        {
          "k": "Animales",
          "v": "No permitidos"
        },
        {
          "k": "Accesibilidad",
          "v": "No adaptado para personas con movilidad reducida. Altura mínima requerida: 1,10 m para el recorrido descubrimiento, 1,40 m para el gran recorrido."
        },
        {
          "k": "Contacto",
          "v": "Tel.: +33 4 50 72 51 86 · Móvil: +33 6 70 63 34 73 · Email: info@parcoursaventure-sciez.com",
          "verified": "2026-05-14"
        },
        {
          "k": "Equipo",
          "v": "Material de seguridad proporcionado (arnés, mosquetones, línea de vida continua). Traer zapatos cerrados."
        }
      ],
      "how_to_get_there": {
        "car": "Desde Thonon-les-Bains (9 km), tomar la D1005 dirección Douvaine y luego seguir la señalización hacia Sciez. El parque se encuentra en el 409 route du Moulin de la Glacière, detrás del museo de Prehistoria y Les Aigles du Léman en el Domaine de Coudrée. Aparcamiento gratuito en el lugar.",
        "public_transport": "Línea de autobús Thonon-Douvaine-Ginebra, parada en Sciez. Verificar horarios y conexiones en Thonon Agglomération. El parque es accesible a pie después (aproximadamente 15 minutos desde el centro de Sciez).",
        "bike": "Accesible a través de la cicloruta del Léman (itinerario a lo largo del lago entre Thonon y Ginebra). Aparcamiento de bicicletas disponible en el lugar."
      },
      "when_to_visit": "El mejor período para visitar el Parcours Aventure de Sciez se extiende de abril a noviembre, con apertura total en julio y agosto (todos los días de 11h a 19h). El parque también está abierto los fines de semana y miércoles en abril y noviembre, así como todos los días durante las vacaciones de Pascua y Todos los Santos. En caso de mal tiempo (lluvia fuerte, viento violento), el parque puede cerrar temporalmente por razones de seguridad — se recomienda contactar con el establecimiento antes de desplazarse. Las mañanas de verano son más tranquilas y ofrecen condiciones ideales para disfrutar de la frescura del bosque.",
      "events": null,
      "faq": [
        {
          "q": "¿Cómo reservar en el Parcours Aventure de Sciez?",
          "a": "Reserva en línea en el sitio oficial parcoursaventure-sciez.com o por teléfono al 04 50 72 51 86 (móvil: 06 70 63 34 73). También es posible comprar en el lugar en las cajas del Parcours Aventure de Sciez según disponibilidades. Se recomienda reservar, especialmente en alta temporada."
        },
        {
          "q": "¿Cuál es la tarifa del Parcours Aventure de Sciez?",
          "a": "La tarifa del recorrido descubrimiento en el Parcours Aventure de Sciez es de 14 € para un adulto y 13 € para un niño. El gran recorrido cuesta 20 € para un adulto y 18 € para un niño. Tarifa grupo (a partir de 8 personas): -2 € por entrada. Verificado el 14 de mayo de 2026."
        },
        {
          "q": "¿Cuáles son los horarios del Parcours Aventure de Sciez?",
          "a": "El Parcours Aventure de Sciez está abierto de abril a noviembre: miércoles, fines de semana y días festivos de 11h a 19h. Julio y agosto: todos los días de 11h a 19h. Vacaciones de Pascua y Todos los Santos: todos los días de 11h a 19h. Último briefing a las 17h. Verificado en el sitio oficial el 14 de mayo de 2026 — bajo reserva de modificaciones estacionales."
        },
        {
          "q": "¿Cuál es la altura mínima requerida para el Parcours Aventure de Sciez?",
          "a": "El recorrido descubrimiento del Parcours Aventure de Sciez es accesible desde 5 años con una altura mínima de 1,10 m. El gran recorrido requiere una altura mínima de 1,40 m. Los menores de 18 años deben estar obligatoriamente acompañados por un adulto en los recorridos."
        },
        {
          "q": "¿Hay aparcamiento en el Parcours Aventure de Sciez?",
          "a": "Sí. El Parcours Aventure de Sciez dispone de un aparcamiento gratuito en el lugar en el 409 route du Moulin de la Glacière en Sciez, en el Domaine de Coudrée."
        },
        {
          "q": "¿Se puede hacer picnic en el Parcours Aventure de Sciez?",
          "a": "Sí. El Parcours Aventure de Sciez pone a disposición un área de picnic con mesas gratuitas para comer y descansar entre dos recorridos."
        }
      ],
      "schema_amenities": [
        "Aparcamiento gratuito",
        "Área de picnic",
        "Más de 40 talleres",
        "Material de seguridad proporcionado",
        "Etiqueta Familia Plus"
      ]
    }
  }
}